ASCII_clock/__init__.py
ASCII_clock/clock.py
ascii_clock-0.1.0.dist-info/METADATA
ascii_clock-0.1.0.dist-info/WHEEL
ascii_clock-0.1.0.dist-info/entry_points.txt
ascii_clock-0.1.0.dist-info/top_level.txt
ascii_clock-0.1.0.dist-info/RECORD
