Metadata-Version: 2.1
Name: ascii-clock
Version: 0.1.0
Summary: A simple ASCII art clock for the terminal
Author: DynaDino
Author-email: 1725356000@qq.com
Classifier: Programming Language :: Python :: 3
Classifier: License :: OSI Approved :: MIT License
Classifier: Operating System :: OS Independent
Requires-Python: >=3.6
